Metadata-Version: 2.1
Name: hoothoot-logger
Version: 1.0.3
Summary: Lib to connect with hoothoot
Home-page: https://gitlab.com/victorhdcoelho/hoothoot-logger
Author: Victor Coelho
Author-email: victorhdcoelho@gmail.com
License: UNKNOWN
Platform: UNKNOWN
Classifier: Programming Language :: Python :: 3
Classifier: License :: OSI Approved :: MIT License
Classifier: Operating System :: OS Independent
Requires-Python: >=3.6
